xixibao/__init__.py
xixibao/xixibao.py
xixibao/xixibao_jr.py
xixibao-0.0.4.dist-info/LICENSE
xixibao-0.0.4.dist-info/METADATA
xixibao-0.0.4.dist-info/WHEEL
xixibao-0.0.4.dist-info/top_level.txt
xixibao-0.0.4.dist-info/RECORD
