Metadata-Version: 2.1
Name: xixibao
Version: 0.0.4
Summary: 希希测试包
Home-page: https://github.com/pypa/sampleproject
Author: xixi
Author-email: 11902004@qq.com
License: UNKNOWN
Project-URL: Bug Tracker, https://github.com/pypa/sampleproject/issues
Platform: UNKNOWN
Classifier: Programming Language :: Python :: 3
Classifier: License :: OSI Approved :: MIT License
Classifier: Operating System :: OS Independent
Requires-Python: >=3.6
